tennflow/__init__.py
tennflow/notebook_fetcher.py
tennflow-0.1.dist-info/METADATA
tennflow-0.1.dist-info/WHEEL
tennflow-0.1.dist-info/top_level.txt
tennflow-0.1.dist-info/RECORD
