Metadata-Version: 2.1
Name: tennflow
Version: 0.1
Summary: A package to download Jupyter notebooks from GitHub.
Home-page: https://github.com/saffuanaanvrr/exam/blob/main/lab.ipynb
Author: Your Name
Classifier: Programming Language :: Python :: 3
Classifier: License :: OSI Approved :: MIT License
Classifier: Operating System :: OS Independent
Requires-Python: >=3.6
Requires-Dist: requests
